{
  "Languages": {
    "arabic": {
      "Id": "arabic",
      "Suffix": "",
      "Adjective": "Arabic",
      "Other": true
    },
    "ba": {
      "Id": "ba",
      "Suffix": "",
      "Adjective": "Bosnian",
      "Other": true
    },
    "bg": {
      "Id": "bg",
      "Suffix": "",
      "Adjective": "Bulgarian",
      "Other": true
    },
    "br": {
      "Id": "br",
      "Suffix": "_br",
      "Adjective": "Brazilian Portuguese",
      "Other": false
    },
    "catalan": {
      "Id": "catalan",
      "Suffix": "",
      "Adjective": "Catalan",
      "Other": true
    },
    "cn": {
      "Id": "cn",
      "Suffix": "",
      "Adjective": "Chinese",
      "Other": true
    },
    "cz": {
      "Id": "cz",
      "Suffix": "",
      "Adjective": "Czech",
      "Other": true
    },
    "de": {
      "Id": "de",
      "Suffix": "_de",
      "Adjective": "German",
      "Other": false
    },
    "dk": {
      "Id": "dk",
      "Suffix": "",
      "Adjective": "Danish",
      "Other": true
    },
    "en": {
      "Id": "en",
      "Suffix": "_en",
      "Adjective": "English",
      "Other": false
    },
    "es": {
      "Id": "es",
      "Suffix": "_es",
      "Adjective": "Spanish",
      "Other": false
    },
    "fi": {
      "Id": "fi",
      "Suffix": "",
      "Adjective": "Finnish",
      "Other": true
    },
    "fr": {
      "Id": "fr",
      "Suffix": "_fr",
      "Adjective": "French",
      "Other": false
    },
    "ge": {
      "Id": "ge",
      "Suffix": "",
      "Adjective": "Georgian",
      "Other": true
    },
    "gr": {
      "Id": "gr",
      "Suffix": "",
      "Adjective": "Greek",
      "Other": true
    },
    "hu": {
      "Id": "hu",
      "Suffix": "",
      "Adjective": "Hungarian",
      "Other": true
    },
    "id": {
      "Id": "id",
      "Suffix": "",
      "Adjective": "Indonesian",
      "Other": true
    },
    "il": {
      "Id": "il",
      "Suffix": "",
      "Adjective": "Hebrew",
      "Other": true
    },
    "ir": {
      "Id": "ir",
      "Suffix": "",
      "Adjective": "Iranian",
      "Other": true
    },
    "it": {
      "Id": "it",
      "Suffix": "",
      "Adjective": "Italian",
      "Other": true
    },
    "jp": {
      "Id": "jp",
      "Suffix": "_jp",
      "Adjective": "Japanese",
      "Other": false
    },
    "kr": {
      "Id": "kr",
      "Suffix": "",
      "Adjective": "Korean",
      "Other": true
    },
    "lv": {
      "Id": "lv",
      "Suffix": "",
      "Adjective": "Latvian",
      "Other": true
    },
    "nl": {
      "Id": "nl",
      "Suffix": "",
      "Adjective": "Dutch",
      "Other": true
    },
    "no": {
      "Id": "no",
      "Suffix": "",
      "Adjective": "Norvegian",
      "Other": true
    },
    "np": {
      "Id": "np",
      "Suffix": "",
      "Adjective": "Nepali",
      "Other": true
    },
    "ph": {
      "Id": "ph",
      "Suffix": "",
      "Adjective": "Filipino",
      "Other": true
    },
    "pl": {
      "Id": "pl",
      "Suffix": "",
      "Adjective": "Polish",
      "Other": true
    },
    "pt": {
      "Id": "pt",
      "Suffix": "",
      "Adjective": "Portuguese",
      "Other": true
    },
    "ro": {
      "Id": "ro",
      "Suffix": "",
      "Adjective": "Romanian",
      "Other": true
    },
    "rs": {
      "Id": "rs",
      "Suffix": "",
      "Adjective": "Serbian",
      "Other": true
    },
    "ru": {
      "Id": "ru",
      "Suffix": "",
      "Adjective": "Russian",
      "Other": false
    },
    "se": {
      "Id": "se",
      "Suffix": "",
      "Adjective": "Swedish",
      "Other": true
    },
    "sk": {
      "Id": "sk",
      "Suffix": "",
      "Adjective": "Slovakian",
      "Other": true
    },
    "th": {
      "Id": "th",
      "Suffix": "",
      "Adjective": "Thai",
      "Other": true
    },
    "tr": {
      "Id": "tr",
      "Suffix": "",
      "Adjective": "Turkish",
      "Other": true
    },
    "ua": {
      "Id": "ua",
      "Suffix": "",
      "Adjective": "Ukrainian",
      "Other": true
    },
    "vn": {
      "Id": "vn",
      "Suffix": "",
      "Adjective": "Vietnamese",
      "Other": true
    }
  },
  "Lang": {
    "Id": "de",
    "Suffix": "_de",
    "Adjective": "German",
    "Other": false
  },
  "Users": {
    "the_ptoing": {
      "PublicName": "Sven \"ptoing\" Ruthner",
      "AvatarImage": "https://pbs.twimg.com/profile_images/702027167299936256/aamngrYc_normal.png",
      "Login": "the_ptoing",
      "CurrentFollowersCount": 9637,
      "CurrentTweetsCout": 15181,
      "FollowersCountHistory": {},
      "TweetsCountHistory": {},
      "LangId": "de",
      "FollowersTrend": {
        "ErrorMessage": null,
        "WeeklyGrowth": -0.0088924458672357832021703496,
        "WeeklyTrendLine": {
          "Start": {
            "X": 20211218.0,
            "Y": 9639.0000000000000000000000
          },
          "End": {
            "X": 20211224.0,
            "Y": 9638.1428571428571428571428
          }
        }
      }
    },
    "moertel": {
      "PublicName": "Stefanie Grunwald 🇪🇺",
      "AvatarImage": "https://pbs.twimg.com/profile_images/1462430044492640260/k_-in1jt_normal.jpg",
      "Login": "moertel",
      "CurrentFollowersCount": 16000,
      "CurrentTweetsCout": 1447,
      "FollowersCountHistory": {},
      "TweetsCountHistory": {},
      "LangId": "de",
      "FollowersTrend": {
        "ErrorMessage": null,
        "WeeklyGrowth": 0.1946130220718010204880447207,
        "WeeklyTrendLine": {
          "Start": {
            "X": 20211218.0,
            "Y": 15965.75000000000000000000
          },
          "End": {
            "X": 20211224.0,
            "Y": 15996.82142857142857142857
          }
        }
      }
    },
    "StuntmAEn_Bob": {
      "PublicName": "StuntmAEn Bob",
      "AvatarImage": "https://pbs.twimg.com/profile_images/1457577295393218565/ZKdaKHPy_normal.jpg",
      "Login": "StuntmAEn_Bob",
      "CurrentFollowersCount": 8531,
      "CurrentTweetsCout": 8666,
      "FollowersCountHistory": {},
      "TweetsCountHistory": {},
      "LangId": "de",
      "FollowersTrend": {
        "ErrorMessage": null,
        "WeeklyGrowth": 1.4402426745179010693483053043,
        "WeeklyTrendLine": {
          "Start": {
            "X": 20211218.0,
            "Y": 8406.32142857142857142857
          },
          "End": {
            "X": 20211224.0,
            "Y": 8527.39285714285714285714
          }
        }
      }
    },
    "eBoyArts": {
      "PublicName": "eBoy",
      "AvatarImage": "https://pbs.twimg.com/profile_images/1466924988586283010/nNnk54TM_normal.jpg",
      "Login": "eBoyArts",
      "CurrentFollowersCount": 12021,
      "CurrentTweetsCout": 3994,
      "FollowersCountHistory": {},
      "TweetsCountHistory": {},
      "LangId": "de",
      "FollowersTrend": {
        "ErrorMessage": null,
        "WeeklyGrowth": 0.4871292802903672572711564024,
        "WeeklyTrendLine": {
          "Start": {
            "X": 20211218.0,
            "Y": 11965.14285714285714285715
          },
          "End": {
            "X": 20211224.0,
            "Y": 12023.42857142857142857144
          }
        }
      }
    },
    "GermanPixelArt": {
      "PublicName": "Moritz",
      "AvatarImage": "https://pbs.twimg.com/profile_images/1464887853343813632/rhvjzzVW_normal.jpg",
      "Login": "GermanPixelArt",
      "CurrentFollowersCount": 51,
      "CurrentTweetsCout": 707,
      "FollowersCountHistory": {},
      "TweetsCountHistory": {},
      "LangId": "de",
      "FollowersTrend": {
        "ErrorMessage": null,
        "WeeklyGrowth": 0.0,
        "WeeklyTrendLine": {
          "Start": {
            "X": 20211218.0,
            "Y": 51.0
          },
          "End": {
            "X": 20211224.0,
            "Y": 51.0
          }
        }
      }
    },
    "Numo_0": {
      "PublicName": "numo.eth (🐻,🐻)",
      "AvatarImage": "https://pbs.twimg.com/profile_images/1472325246560751626/pLQl4C0t_normal.jpg",
      "Login": "Numo_0",
      "CurrentFollowersCount": 6157,
      "CurrentTweetsCout": 26675,
      "FollowersCountHistory": {},
      "TweetsCountHistory": {},
      "LangId": "de",
      "FollowersTrend": {
        "ErrorMessage": null,
        "WeeklyGrowth": 2.4766920503878727492704659328,
        "WeeklyTrendLine": {
          "Start": {
            "X": 20211218.0,
            "Y": 6021.85714285714285714286
          },
          "End": {
            "X": 20211224.0,
            "Y": 6171.00000000000000000000
          }
        }
      }
    },
    "TassiloRau": {
      "PublicName": "Tassilo",
      "AvatarImage": "https://pbs.twimg.com/profile_images/1098511260461789185/5oyO0ff1_normal.png",
      "Login": "TassiloRau",
      "CurrentFollowersCount": 772,
      "CurrentTweetsCout": 4208,
      "FollowersCountHistory": {},
      "TweetsCountHistory": {},
      "LangId": "de",
      "FollowersTrend": {
        "ErrorMessage": null,
        "WeeklyGrowth": 0.0,
        "WeeklyTrendLine": {
          "Start": {
            "X": 20211218.0,
            "Y": 772.0
          },
          "End": {
            "X": 20211224.0,
            "Y": 772.0
          }
        }
      }
    },
    "BenstarDEV": {
      "PublicName": "BenStar 🏳️‍🌈",
      "AvatarImage": "https://pbs.twimg.com/profile_images/1469073109705797632/k5UtsSdp_normal.jpg",
      "Login": "BenstarDEV",
      "CurrentFollowersCount": 16170,
      "CurrentTweetsCout": 29810,
      "FollowersCountHistory": {},
      "TweetsCountHistory": {},
      "LangId": "de",
      "FollowersTrend": {
        "ErrorMessage": null,
        "WeeklyGrowth": 0.030499192213423622729415144,
        "WeeklyTrendLine": {
          "Start": {
            "X": 20211218.0,
            "Y": 16159.678571428571428571429
          },
          "End": {
            "X": 20211224.0,
            "Y": 16164.607142857142857142858
          }
        }
      }
    },
    "NiRi_0": {
      "PublicName": "니리",
      "AvatarImage": "https://pbs.twimg.com/profile_images/1396434253081038853/0o4x5Fj0_normal.jpg",
      "Login": "NiRi_0",
      "CurrentFollowersCount": 3,
      "CurrentTweetsCout": 1,
      "FollowersCountHistory": {},
      "TweetsCountHistory": {},
      "LangId": "de",
      "FollowersTrend": {
        "ErrorMessage": null,
        "WeeklyGrowth": 0.0,
        "WeeklyTrendLine": {
          "Start": {
            "X": 20211101.0,
            "Y": 3.0
          },
          "End": {
            "X": 20211107.0,
            "Y": 3.0
          }
        }
      }
    },
    "FedericoCalch": {
      "PublicName": "Federico Calchera",
      "AvatarImage": "https://pbs.twimg.com/profile_images/1289989462496337925/fUc9ONeV_normal.jpg",
      "Login": "FedericoCalch",
      "CurrentFollowersCount": 196,
      "CurrentTweetsCout": 72,
      "FollowersCountHistory": {},
      "TweetsCountHistory": {},
      "LangId": "de",
      "FollowersTrend": {
        "ErrorMessage": null,
        "WeeklyGrowth": 0.1093892433910665451230599802,
        "WeeklyTrendLine": {
          "Start": {
            "X": 20211218.0,
            "Y": 195.89285714285714285714286
          },
          "End": {
            "X": 20211224.0,
            "Y": 196.10714285714285714285714
          }
        }
      }
    },
    "PretzelBros": {
      "PublicName": "Alex Schaefer",
      "AvatarImage": "https://pbs.twimg.com/profile_images/1469028346919104523/d_5-N3qB_normal.png",
      "Login": "PretzelBros",
      "CurrentFollowersCount": 746,
      "CurrentTweetsCout": 154,
      "FollowersCountHistory": {},
      "TweetsCountHistory": {},
      "LangId": "de",
      "FollowersTrend": {
        "ErrorMessage": null,
        "WeeklyGrowth": -0.2576950608446671438797461079,
        "WeeklyTrendLine": {
          "Start": {
            "X": 20211218.0,
            "Y": 748.3928571428571428571429
          },
          "End": {
            "X": 20211224.0,
            "Y": 746.4642857142857142857143
          }
        }
      }
    },
    "cyangmou": {
      "PublicName": "Thomas Feichtmeir",
      "AvatarImage": "https://pbs.twimg.com/profile_images/1386328539461529604/yQPCt8vi_normal.png",
      "Login": "cyangmou",
      "CurrentFollowersCount": 48597,
      "CurrentTweetsCout": 11190,
      "FollowersCountHistory": {},
      "TweetsCountHistory": {},
      "LangId": "de",
      "FollowersTrend": {
        "ErrorMessage": null,
        "WeeklyGrowth": 0.0560263220778265904453916227,
        "WeeklyTrendLine": {
          "Start": {
            "X": 20211218.0,
            "Y": 48574.10714285714285714285
          },
          "End": {
            "X": 20211224.0,
            "Y": 48601.32142857142857142857
          }
        }
      }
    },
    "Hammster1911": {
      "PublicName": "🧙 Hans Koch",
      "AvatarImage": "https://pbs.twimg.com/profile_images/1290327867532947463/Wb4jeXED_normal.jpg",
      "Login": "Hammster1911",
      "CurrentFollowersCount": 116,
      "CurrentTweetsCout": 890,
      "FollowersCountHistory": {},
      "TweetsCountHistory": {},
      "LangId": "de",
      "FollowersTrend": {
        "ErrorMessage": null,
        "WeeklyGrowth": 0.0,
        "WeeklyTrendLine": {
          "Start": {
            "X": 20211218.0,
            "Y": 116.0
          },
          "End": {
            "X": 20211224.0,
            "Y": 116.0
          }
        }
      }
    },
    "visionvortex": {
      "PublicName": "Richard Schmidbauer",
      "AvatarImage": "https://pbs.twimg.com/profile_images/1416127181139365897/kR3v-WNu_normal.jpg",
      "Login": "visionvortex",
      "CurrentFollowersCount": 2835,
      "CurrentTweetsCout": 4105,
      "FollowersCountHistory": {},
      "TweetsCountHistory": {},
      "LangId": "de",
      "FollowersTrend": {
        "ErrorMessage": null,
        "WeeklyGrowth": 0.2652218391240101542075550737,
        "WeeklyTrendLine": {
          "Start": {
            "X": 20211218.0,
            "Y": 2827.821428571428571428571
          },
          "End": {
            "X": 20211224.0,
            "Y": 2835.321428571428571428571
          }
        }
      }
    },
    "MandrillPixel": {
      "PublicName": "Mandrill Pixel",
      "AvatarImage": "https://pbs.twimg.com/profile_images/683302871815864320/TDAFY5Wa_normal.png",
      "Login": "MandrillPixel",
      "CurrentFollowersCount": 4902,
      "CurrentTweetsCout": 2322,
      "FollowersCountHistory": {},
      "TweetsCountHistory": {},
      "LangId": "de",
      "FollowersTrend": {
        "ErrorMessage": null,
        "WeeklyGrowth": 0.2410254537486761859547953321,
        "WeeklyTrendLine": {
          "Start": {
            "X": 20211218.0,
            "Y": 4889.821428571428571428571
          },
          "End": {
            "X": 20211224.0,
            "Y": 4901.607142857142857142857
          }
        }
      }
    },
    "vierbit": {
      "PublicName": "Vierbit",
      "AvatarImage": "https://pbs.twimg.com/profile_images/778601526298304512/oHq9LXgO_normal.jpg",
      "Login": "vierbit",
      "CurrentFollowersCount": 6467,
      "CurrentTweetsCout": 42,
      "FollowersCountHistory": {},
      "TweetsCountHistory": {},
      "LangId": "de",
      "FollowersTrend": {
        "ErrorMessage": null,
        "WeeklyGrowth": 0.0430965417787821359309173476,
        "WeeklyTrendLine": {
          "Start": {
            "X": 20211218.0,
            "Y": 6463.892857142857142857143
          },
          "End": {
            "X": 20211224.0,
            "Y": 6466.678571428571428571429
          }
        }
      }
    },
    "MimicMango": {
      "PublicName": "DieMango",
      "AvatarImage": "https://pbs.twimg.com/profile_images/1277189850026958849/u5NvIG5Q_normal.jpg",
      "Login": "MimicMango",
      "CurrentFollowersCount": 39629,
      "CurrentTweetsCout": 14557,
      "FollowersCountHistory": {},
      "TweetsCountHistory": {},
      "LangId": "de",
      "FollowersTrend": {
        "ErrorMessage": null,
        "WeeklyGrowth": 2.1073167511787533771982546944,
        "WeeklyTrendLine": {
          "Start": {
            "X": 20211218.0,
            "Y": 38956.1071428571428571429
          },
          "End": {
            "X": 20211224.0,
            "Y": 39777.0357142857142857143
          }
        }
      }
    },
    "dennisbusch_de": {
      "PublicName": "0xDB",
      "AvatarImage": "https://pbs.twimg.com/profile_images/520255209298067456/b3_pvPJH_normal.png",
      "Login": "dennisbusch_de",
      "CurrentFollowersCount": 309,
      "CurrentTweetsCout": 954,
      "FollowersCountHistory": {},
      "TweetsCountHistory": {},
      "LangId": "de",
      "FollowersTrend": {
        "ErrorMessage": null,
        "WeeklyGrowth": 0.0,
        "WeeklyTrendLine": {
          "Start": {
            "X": 20211218.0,
            "Y": 309.0
          },
          "End": {
            "X": 20211224.0,
            "Y": 309.0
          }
        }
      }
    },
    "MrValenberg": {
      "PublicName": "Valenberg",
      "AvatarImage": "https://pbs.twimg.com/profile_images/883324208805273600/gupxxJdf_normal.jpg",
      "Login": "MrValenberg",
      "CurrentFollowersCount": 13504,
      "CurrentTweetsCout": 5489,
      "FollowersCountHistory": {},
      "TweetsCountHistory": {},
      "LangId": "de",
      "FollowersTrend": {
        "ErrorMessage": null,
        "WeeklyGrowth": -0.0206236267440845885983093912,
        "WeeklyTrendLine": {
          "Start": {
            "X": 20211218.0,
            "Y": 13507.392857142857142857143
          },
          "End": {
            "X": 20211224.0,
            "Y": 13504.607142857142857142857
          }
        }
      }
    },
    "tomicpixel": {
      "PublicName": "tomicpixel",
      "AvatarImage": "https://pbs.twimg.com/profile_images/1079443341094334465/hWjwMUgq_normal.jpg",
      "Login": "tomicpixel",
      "CurrentFollowersCount": 1107,
      "CurrentTweetsCout": 228,
      "FollowersCountHistory": {},
      "TweetsCountHistory": {},
      "LangId": "de",
      "FollowersTrend": {
        "ErrorMessage": null,
        "WeeklyGrowth": -0.1352526325958844556081538033,
        "WeeklyTrendLine": {
          "Start": {
            "X": 20211218.0,
            "Y": 1109.0357142857142857142857
          },
          "End": {
            "X": 20211224.0,
            "Y": 1107.5357142857142857142857
          }
        }
      }
    },
    "Trick_Siebzehn": {
      "PublicName": "Fabian",
      "AvatarImage": "https://pbs.twimg.com/profile_images/1011242423274569728/6CASLid3_normal.jpg",
      "Login": "Trick_Siebzehn",
      "CurrentFollowersCount": 7351,
      "CurrentTweetsCout": 627,
      "FollowersCountHistory": {},
      "TweetsCountHistory": {},
      "LangId": "de",
      "FollowersTrend": {
        "ErrorMessage": null,
        "WeeklyGrowth": 0.096274937883215582925293575,
        "WeeklyTrendLine": {
          "Start": {
            "X": 20211218.0,
            "Y": 7345.035714285714285714285
          },
          "End": {
            "X": 20211224.0,
            "Y": 7352.107142857142857142856
          }
        }
      }
    },
    "blancablancovic": {
      "PublicName": "blancablancovic",
      "AvatarImage": "https://pbs.twimg.com/profile_images/733561499063459842/Wzk9IIeO_normal.jpg",
      "Login": "blancablancovic",
      "CurrentFollowersCount": 83,
      "CurrentTweetsCout": 197,
      "FollowersCountHistory": {},
      "TweetsCountHistory": {},
      "LangId": "de",
      "FollowersTrend": {
        "ErrorMessage": null,
        "WeeklyGrowth": 1.3106159895150720838793883792,
        "WeeklyTrendLine": {
          "Start": {
            "X": 20211218.0,
            "Y": 81.7500000000000000000000
          },
          "End": {
            "X": 20211224.0,
            "Y": 82.8214285714285714285714
          }
        }
      }
    },
    "Pixellance": {
      "PublicName": "Pixellance",
      "AvatarImage": "https://pbs.twimg.com/profile_images/1300134617710825473/oZhGYuZh_normal.jpg",
      "Login": "Pixellance",
      "CurrentFollowersCount": 302,
      "CurrentTweetsCout": 1127,
      "FollowersCountHistory": {},
      "TweetsCountHistory": {},
      "LangId": "de",
      "FollowersTrend": {
        "ErrorMessage": null,
        "WeeklyGrowth": 0.0,
        "WeeklyTrendLine": {
          "Start": {
            "X": 20211218.0,
            "Y": 302.0
          },
          "End": {
            "X": 20211224.0,
            "Y": 302.0
          }
        }
      }
    },
    "BANDOS7de": {
      "PublicName": "BANDOS7",
      "AvatarImage": "https://pbs.twimg.com/profile_images/1426307532524597250/1G-bpxn5_normal.jpg",
      "Login": "BANDOS7de",
      "CurrentFollowersCount": 1402,
      "CurrentTweetsCout": 3735,
      "FollowersCountHistory": {},
      "TweetsCountHistory": {},
      "LangId": "de",
      "FollowersTrend": {
        "ErrorMessage": null,
        "WeeklyGrowth": 0.0764428589629252134029792299,
        "WeeklyTrendLine": {
          "Start": {
            "X": 20211218.0,
            "Y": 1401.6071428571428571428572
          },
          "End": {
            "X": 20211224.0,
            "Y": 1402.6785714285714285714286
          }
        }
      }
    },
    "official_Niruki": {
      "PublicName": "Niruki Entertainment 🏳️‍🌈",
      "AvatarImage": "https://pbs.twimg.com/profile_images/1407848744322842627/D78P41yI_normal.jpg",
      "Login": "official_Niruki",
      "CurrentFollowersCount": 39,
      "CurrentTweetsCout": 262,
      "FollowersCountHistory": {},
      "TweetsCountHistory": {},
      "LangId": "de",
      "FollowersTrend": {
        "ErrorMessage": null,
        "WeeklyGrowth": 0.0,
        "WeeklyTrendLine": {
          "Start": {
            "X": 20211218.0,
            "Y": 39.0
          },
          "End": {
            "X": 20211224.0,
            "Y": 39.0
          }
        }
      }
    },
    "s4m_ur4i": {
      "PublicName": "sᴀᴍ ツ",
      "AvatarImage": "https://pbs.twimg.com/profile_images/1444578304946843651/Otsqo3tX_normal.jpg",
      "Login": "s4m_ur4i",
      "CurrentFollowersCount": 1642,
      "CurrentTweetsCout": 4596,
      "FollowersCountHistory": {},
      "TweetsCountHistory": {},
      "LangId": "de",
      "FollowersTrend": {
        "ErrorMessage": null,
        "WeeklyGrowth": -0.1172918612480722865396746237,
        "WeeklyTrendLine": {
          "Start": {
            "X": 20211218.0,
            "Y": 1644.2500000000000000000000
          },
          "End": {
            "X": 20211224.0,
            "Y": 1642.3214285714285714285714
          }
        }
      }
    },
    "max_ritters": {
      "PublicName": "Max Ritters",
      "AvatarImage": "https://pbs.twimg.com/profile_images/1167178080345120769/z3pznhiP_normal.jpg",
      "Login": "max_ritters",
      "CurrentFollowersCount": 111,
      "CurrentTweetsCout": 625,
      "FollowersCountHistory": {},
      "TweetsCountHistory": {},
      "LangId": "de",
      "FollowersTrend": {
        "ErrorMessage": null,
        "WeeklyGrowth": 0.5815831987075928917608530639,
        "WeeklyTrendLine": {
          "Start": {
            "X": 20211218.0,
            "Y": 110.5357142857142857142857
          },
          "End": {
            "X": 20211224.0,
            "Y": 111.1785714285714285714285
          }
        }
      }
    },
    "jonkellerdev": {
      "PublicName": "Jon Keller",
      "AvatarImage": "https://pbs.twimg.com/profile_images/1471774402798919682/UR4mHGW1_normal.jpg",
      "Login": "jonkellerdev",
      "CurrentFollowersCount": 8800,
      "CurrentTweetsCout": 1041,
      "FollowersCountHistory": {},
      "TweetsCountHistory": {},
      "LangId": "de",
      "FollowersTrend": {
        "ErrorMessage": null,
        "WeeklyGrowth": 0.0024351736481742285572813072,
        "WeeklyTrendLine": {
          "Start": {
            "X": 20211218.0,
            "Y": 8799.60714285714285714285715
          },
          "End": {
            "X": 20211224.0,
            "Y": 8799.82142857142857142857143
          }
        }
      }
    },
    "DanielRachtan": {
      "PublicName": "Daniel Rachtan",
      "AvatarImage": "https://pbs.twimg.com/profile_images/785736158793830401/Vd9uSnm5_normal.jpg",
      "Login": "DanielRachtan",
      "CurrentFollowersCount": 540,
      "CurrentTweetsCout": 19,
      "FollowersCountHistory": {},
      "TweetsCountHistory": {},
      "LangId": "de",
      "FollowersTrend": {
        "ErrorMessage": null,
        "WeeklyGrowth": -0.2375610399894417315560221661,
        "WeeklyTrendLine": {
          "Start": {
            "X": 20211218.0,
            "Y": 541.2142857142857142857143
          },
          "End": {
            "X": 20211224.0,
            "Y": 539.9285714285714285714286
          }
        }
      }
    },
    "Tom_HirschEOD": {
      "PublicName": "Tom Hirsch",
      "AvatarImage": "https://pbs.twimg.com/profile_images/1430794054128881667/MIEwx_gB_normal.jpg",
      "Login": "Tom_HirschEOD",
      "CurrentFollowersCount": 609,
      "CurrentTweetsCout": 436,
      "FollowersCountHistory": {},
      "TweetsCountHistory": {},
      "LangId": "de",
      "FollowersTrend": {
        "ErrorMessage": null,
        "WeeklyGrowth": -0.2106988177455226501229052977,
        "WeeklyTrendLine": {
          "Start": {
            "X": 20211218.0,
            "Y": 610.2142857142857142857143
          },
          "End": {
            "X": 20211224.0,
            "Y": 608.9285714285714285714286
          }
        }
      }
    },
    "zlohlednihcs": {
      "PublicName": "Pixelplanes",
      "AvatarImage": "https://pbs.twimg.com/profile_images/1222184096274821130/XJxufale_normal.png",
      "Login": "zlohlednihcs",
      "CurrentFollowersCount": 443,
      "CurrentTweetsCout": 333,
      "FollowersCountHistory": {},
      "TweetsCountHistory": {},
      "LangId": "de",
      "FollowersTrend": {
        "ErrorMessage": null,
        "WeeklyGrowth": 1.1235040299601074656029623478,
        "WeeklyTrendLine": {
          "Start": {
            "X": 20211218.0,
            "Y": 438.678571428571428571429
          },
          "End": {
            "X": 20211224.0,
            "Y": 443.607142857142857142858
          }
        }
      }
    },
    "Colorflo14": {
      "PublicName": "colorflo",
      "AvatarImage": "https://pbs.twimg.com/profile_images/1206853202576105474/_PUkKt92_normal.png",
      "Login": "Colorflo14",
      "CurrentFollowersCount": 228,
      "CurrentTweetsCout": 326,
      "FollowersCountHistory": {},
      "TweetsCountHistory": {},
      "LangId": "de",
      "FollowersTrend": {
        "ErrorMessage": null,
        "WeeklyGrowth": 0.1885014137606032045240465325,
        "WeeklyTrendLine": {
          "Start": {
            "X": 20211218.0,
            "Y": 227.3571428571428571428571
          },
          "End": {
            "X": 20211224.0,
            "Y": 227.7857142857142857142857
          }
        }
      }
    },
    "dr_smey": {
      "PublicName": "DrSmey",
      "AvatarImage": "https://pbs.twimg.com/profile_images/1379837263878717442/z45wdEzH_normal.png",
      "Login": "dr_smey",
      "CurrentFollowersCount": 2760,
      "CurrentTweetsCout": 659,
      "FollowersCountHistory": {},
      "TweetsCountHistory": {},
      "LangId": "de",
      "FollowersTrend": {
        "ErrorMessage": null,
        "WeeklyGrowth": 0.3033170440846695270068777788,
        "WeeklyTrendLine": {
          "Start": {
            "X": 20211218.0,
            "Y": 2755.250000000000000000000
          },
          "End": {
            "X": 20211224.0,
            "Y": 2763.607142857142857142857
          }
        }
      }
    },
    "e_Pics_": {
      "PublicName": "ePics",
      "AvatarImage": "https://pbs.twimg.com/profile_images/1261628509308452864/G8DvKxl6_normal.jpg",
      "Login": "e_Pics_",
      "CurrentFollowersCount": 170,
      "CurrentTweetsCout": 103,
      "FollowersCountHistory": {},
      "TweetsCountHistory": {},
      "LangId": "de",
      "FollowersTrend": {
        "ErrorMessage": null,
        "WeeklyGrowth": -1.4913007456503728251861603365,
        "WeeklyTrendLine": {
          "Start": {
            "X": 20211218.0,
            "Y": 172.428571428571428571429
          },
          "End": {
            "X": 20211224.0,
            "Y": 169.857142857142857142858
          }
        }
      }
    },
    "nuraray_pix": {
      "PublicName": "Nura Fuks",
      "AvatarImage": "https://pbs.twimg.com/profile_images/1261717241525141506/47_0DrfX_normal.jpg",
      "Login": "nuraray_pix",
      "CurrentFollowersCount": 59,
      "CurrentTweetsCout": 37,
      "FollowersCountHistory": {},
      "TweetsCountHistory": {},
      "LangId": "de",
      "FollowersTrend": {
        "ErrorMessage": null,
        "WeeklyGrowth": 0.0,
        "WeeklyTrendLine": {
          "Start": {
            "X": 20211218.0,
            "Y": 59.0
          },
          "End": {
            "X": 20211224.0,
            "Y": 59.0
          }
        }
      }
    },
    "Noggi19": {
      "PublicName": "Noggi",
      "AvatarImage": "https://pbs.twimg.com/profile_images/1394435170330202113/4IjhkB8Q_normal.jpg",
      "Login": "Noggi19",
      "CurrentFollowersCount": 535,
      "CurrentTweetsCout": 2239,
      "FollowersCountHistory": {},
      "TweetsCountHistory": {},
      "LangId": "de",
      "FollowersTrend": {
        "ErrorMessage": null,
        "WeeklyGrowth": 0.5227531666778366061256482748,
        "WeeklyTrendLine": {
          "Start": {
            "X": 20211218.0,
            "Y": 532.892857142857142857143
          },
          "End": {
            "X": 20211224.0,
            "Y": 535.678571428571428571429
          }
        }
      }
    },
    "Sleepy_Pixels": {
      "PublicName": "Noël Kalunder",
      "AvatarImage": "https://pbs.twimg.com/profile_images/1302733835575209985/uUVw84t5_normal.png",
      "Login": "Sleepy_Pixels",
      "CurrentFollowersCount": 635,
      "CurrentTweetsCout": 1027,
      "FollowersCountHistory": {},
      "TweetsCountHistory": {},
      "LangId": "de",
      "FollowersTrend": {
        "ErrorMessage": null,
        "WeeklyGrowth": -0.1012088838909193140286668655,
        "WeeklyTrendLine": {
          "Start": {
            "X": 20211218.0,
            "Y": 635.1785714285714285714285
          },
          "End": {
            "X": 20211224.0,
            "Y": 634.5357142857142857142857
          }
        }
      }
    },
    "foofarawr": {
      "PublicName": "✨Foofarawr✨",
      "AvatarImage": "https://pbs.twimg.com/profile_images/1315011917312819200/0ys9QHjI_normal.jpg",
      "Login": "foofarawr",
      "CurrentFollowersCount": 2386,
      "CurrentTweetsCout": 912,
      "FollowersCountHistory": {},
      "TweetsCountHistory": {},
      "LangId": "de",
      "FollowersTrend": {
        "ErrorMessage": null,
        "WeeklyGrowth": 0.66334489391025155613443172,
        "WeeklyTrendLine": {
          "Start": {
            "X": 20211218.0,
            "Y": 2358.178571428571428571429
          },
          "End": {
            "X": 20211224.0,
            "Y": 2373.821428571428571428572
          }
        }
      }
    },
    "sKaule": {
      "PublicName": "Steven Kaule",
      "AvatarImage": "https://pbs.twimg.com/profile_images/1360609813126864899/kn9CZnEH_normal.jpg",
      "Login": "sKaule",
      "CurrentFollowersCount": 1826,
      "CurrentTweetsCout": 692,
      "FollowersCountHistory": {},
      "TweetsCountHistory": {},
      "LangId": "de",
      "FollowersTrend": {
        "ErrorMessage": null,
        "WeeklyGrowth": -0.1640432761785728234972463908,
        "WeeklyTrendLine": {
          "Start": {
            "X": 20211218.0,
            "Y": 1828.785714285714285714286
          },
          "End": {
            "X": 20211224.0,
            "Y": 1825.785714285714285714286
          }
        }
      }
    },
    "LastStarfarer": {
      "PublicName": "Yuri Stern | SIGNALIS",
      "AvatarImage": "https://pbs.twimg.com/profile_images/1014241500878778368/4TjSdZMa_normal.jpg",
      "Login": "LastStarfarer",
      "CurrentFollowersCount": 9179,
      "CurrentTweetsCout": 2635,
      "FollowersCountHistory": {},
      "TweetsCountHistory": {},
      "LangId": "de",
      "FollowersTrend": {
        "ErrorMessage": null,
        "WeeklyGrowth": -0.0653096767171002503537607489,
        "WeeklyTrendLine": {
          "Start": {
            "X": 20211218.0,
            "Y": 9187.0
          },
          "End": {
            "X": 20211224.0,
            "Y": 9181.0
          }
        }
      }
    },
    "wolve_rain": {
      "PublicName": "𝖂𝖔𝖑𝖛𝖊_𝕽𝖆𝖎𝖓 🦇📌Drawing Challenge🦇",
      "AvatarImage": "https://pbs.twimg.com/profile_images/1472939591615324166/uQfIItYQ_normal.jpg",
      "Login": "wolve_rain",
      "CurrentFollowersCount": 651,
      "CurrentTweetsCout": 9297,
      "FollowersCountHistory": {},
      "TweetsCountHistory": {},
      "LangId": "de",
      "FollowersTrend": {
        "ErrorMessage": null,
        "WeeklyGrowth": 0.5956977385548814120242471042,
        "WeeklyTrendLine": {
          "Start": {
            "X": 20211218.0,
            "Y": 647.500000000000000000000
          },
          "End": {
            "X": 20211224.0,
            "Y": 651.357142857142857142857
          }
        }
      }
    },
    "cmmrc2": {
      "PublicName": "ink (commissions closed)",
      "AvatarImage": "https://pbs.twimg.com/profile_images/1437335979027742723/VVdmkqKC_normal.png",
      "Login": "cmmrc2",
      "CurrentFollowersCount": 1853,
      "CurrentTweetsCout": 432,
      "FollowersCountHistory": {},
      "TweetsCountHistory": {},
      "LangId": "de",
      "FollowersTrend": {
        "ErrorMessage": null,
        "WeeklyGrowth": 0.3249013692271988860524484142,
        "WeeklyTrendLine": {
          "Start": {
            "X": 20211218.0,
            "Y": 1846.714285714285714285714
          },
          "End": {
            "X": 20211224.0,
            "Y": 1852.714285714285714285714
          }
        }
      }
    },
    "Pixellover99": {
      "PublicName": "Pixellover",
      "AvatarImage": "https://pbs.twimg.com/profile_images/1296323659079004160/4wIHnUCW_normal.jpg",
      "Login": "Pixellover99",
      "CurrentFollowersCount": 109,
      "CurrentTweetsCout": 2294,
      "FollowersCountHistory": {},
      "TweetsCountHistory": {},
      "LangId": "de",
      "FollowersTrend": {
        "ErrorMessage": null,
        "WeeklyGrowth": 0.0,
        "WeeklyTrendLine": {
          "Start": {
            "X": 20211218.0,
            "Y": 109.0
          },
          "End": {
            "X": 20211224.0,
            "Y": 109.0
          }
        }
      }
    },
    "Welteninsel_K": {
      "PublicName": "Welteninsel",
      "AvatarImage": "https://pbs.twimg.com/profile_images/1464354038795886594/boJAWFYO_normal.png",
      "Login": "Welteninsel_K",
      "CurrentFollowersCount": 120,
      "CurrentTweetsCout": 656,
      "FollowersCountHistory": {},
      "TweetsCountHistory": {},
      "LangId": "de",
      "FollowersTrend": {
        "ErrorMessage": null,
        "WeeklyGrowth": 0.0,
        "WeeklyTrendLine": {
          "Start": {
            "X": 20211218.0,
            "Y": 120.0
          },
          "End": {
            "X": 20211224.0,
            "Y": 120.0
          }
        }
      }
    },
    "dinchensart": {
      "PublicName": "Dinchen 🍂",
      "AvatarImage": "https://pbs.twimg.com/profile_images/1442811415233024000/1NCETX3z_normal.jpg",
      "Login": "dinchensart",
      "CurrentFollowersCount": 2646,
      "CurrentTweetsCout": 2538,
      "FollowersCountHistory": {},
      "TweetsCountHistory": {},
      "LangId": "de",
      "FollowersTrend": {
        "ErrorMessage": null,
        "WeeklyGrowth": 0.0,
        "WeeklyTrendLine": {
          "Start": {
            "X": 20211218.0,
            "Y": 2644.5714285714285714285714286
          },
          "End": {
            "X": 20211224.0,
            "Y": 2644.5714285714285714285714286
          }
        }
      }
    },
    "SilvioMilvio": {
      "PublicName": "Silvio M.",
      "AvatarImage": "https://pbs.twimg.com/profile_images/852077161318162434/Yx6k_sO6_normal.jpg",
      "Login": "SilvioMilvio",
      "CurrentFollowersCount": 187,
      "CurrentTweetsCout": 772,
      "FollowersCountHistory": {},
      "TweetsCountHistory": {},
      "LangId": "de",
      "FollowersTrend": {
        "ErrorMessage": null,
        "WeeklyGrowth": -0.5691519635742743312464276228,
        "WeeklyTrendLine": {
          "Start": {
            "X": 20211218.0,
            "Y": 188.2500000000000000000000
          },
          "End": {
            "X": 20211224.0,
            "Y": 187.1785714285714285714286
          }
        }
      }
    },
    "sabbi_tabbi": {
      "PublicName": "Saboo Taboo🎩",
      "AvatarImage": "https://pbs.twimg.com/profile_images/1311444957035663361/AJH0pRGu_normal.jpg",
      "Login": "sabbi_tabbi",
      "CurrentFollowersCount": 4382,
      "CurrentTweetsCout": 16143,
      "FollowersCountHistory": {},
      "TweetsCountHistory": {},
      "LangId": "de",
      "FollowersTrend": {
        "ErrorMessage": null,
        "WeeklyGrowth": 0.1962130874129304424605023312,
        "WeeklyTrendLine": {
          "Start": {
            "X": 20211218.0,
            "Y": 4368.428571428571428571428
          },
          "End": {
            "X": 20211224.0,
            "Y": 4376.999999999999999999999
          }
        }
      }
    },
    "P_Cat_": {
      "PublicName": "PCatGames",
      "AvatarImage": "https://pbs.twimg.com/profile_images/1283808605800747009/UjoIr5N8_normal.jpg",
      "Login": "P_Cat_",
      "CurrentFollowersCount": 4315,
      "CurrentTweetsCout": 8584,
      "FollowersCountHistory": {},
      "TweetsCountHistory": {},
      "LangId": "de",
      "FollowersTrend": {
        "ErrorMessage": null,
        "WeeklyGrowth": -0.1289490651192778852353221204,
        "WeeklyTrendLine": {
          "Start": {
            "X": 20211218.0,
            "Y": 4320.642857142857142857143
          },
          "End": {
            "X": 20211224.0,
            "Y": 4315.071428571428571428572
          }
        }
      }
    },
    "belinhacbr": {
      "PublicName": "𝗯' 🦕",
      "AvatarImage": "https://pbs.twimg.com/profile_images/1325276420420079616/bwIQX7ic_normal.png",
      "Login": "belinhacbr",
      "CurrentFollowersCount": 144,
      "CurrentTweetsCout": 3427,
      "FollowersCountHistory": {},
      "TweetsCountHistory": {},
      "LangId": "de",
      "FollowersTrend": {
        "ErrorMessage": null,
        "WeeklyGrowth": 0.0,
        "WeeklyTrendLine": {
          "Start": {
            "X": 20211218.0,
            "Y": 144.0
          },
          "End": {
            "X": 20211224.0,
            "Y": 144.0
          }
        }
      }
    },
    "mistertabasc0": {
      "PublicName": "mistertabasco",
      "AvatarImage": "https://pbs.twimg.com/profile_images/1274270987249467393/FXLVAUjN_normal.jpg",
      "Login": "mistertabasc0",
      "CurrentFollowersCount": 238,
      "CurrentTweetsCout": 288,
      "FollowersCountHistory": {},
      "TweetsCountHistory": {},
      "LangId": "de",
      "FollowersTrend": {
        "ErrorMessage": null,
        "WeeklyGrowth": 0.5426590292432921314440701063,
        "WeeklyTrendLine": {
          "Start": {
            "X": 20211218.0,
            "Y": 236.9285714285714285714285
          },
          "End": {
            "X": 20211224.0,
            "Y": 238.2142857142857142857142
          }
        }
      }
    },
    "lazybensch": {
      "PublicName": "lazybensch",
      "AvatarImage": "https://pbs.twimg.com/profile_images/1151155682667835392/2nH1blw4_normal.png",
      "Login": "lazybensch",
      "CurrentFollowersCount": 3966,
      "CurrentTweetsCout": 1939,
      "FollowersCountHistory": {},
      "TweetsCountHistory": {},
      "LangId": "de",
      "FollowersTrend": {
        "ErrorMessage": null,
        "WeeklyGrowth": -0.075554516181258882152943925,
        "WeeklyTrendLine": {
          "Start": {
            "X": 20211218.0,
            "Y": 3970.642857142857142857143
          },
          "End": {
            "X": 20211224.0,
            "Y": 3967.642857142857142857143
          }
        }
      }
    },
    "Aniebodie": {
      "PublicName": "Anie",
      "AvatarImage": "https://pbs.twimg.com/profile_images/1443975705985957890/96aBU8Bg_normal.jpg",
      "Login": "Aniebodie",
      "CurrentFollowersCount": 264,
      "CurrentTweetsCout": 1801,
      "FollowersCountHistory": {},
      "TweetsCountHistory": {},
      "LangId": "de",
      "FollowersTrend": {
        "ErrorMessage": null,
        "WeeklyGrowth": 0.4892633867898885566730035602,
        "WeeklyTrendLine": {
          "Start": {
            "X": 20211218.0,
            "Y": 262.7857142857142857142857
          },
          "End": {
            "X": 20211224.0,
            "Y": 264.0714285714285714285714
          }
        }
      }
    },
    "edlixstudios": {
      "PublicName": "Eduard Albrecht",
      "AvatarImage": "https://pbs.twimg.com/profile_images/994912944453570560/bNJD8vaS_normal.jpg",
      "Login": "edlixstudios",
      "CurrentFollowersCount": 101,
      "CurrentTweetsCout": 153,
      "FollowersCountHistory": {},
      "TweetsCountHistory": {},
      "LangId": "de",
      "FollowersTrend": {
        "ErrorMessage": null,
        "WeeklyGrowth": 0.0,
        "WeeklyTrendLine": {
          "Start": {
            "X": 20211218.0,
            "Y": 101.0
          },
          "End": {
            "X": 20211224.0,
            "Y": 101.0
          }
        }
      }
    },
    "SilvanuZ_mit_Z": {
      "PublicName": "SilvanuZ mit Z",
      "AvatarImage": "https://pbs.twimg.com/profile_images/1428266162270449664/Nx3dMLEy_normal.jpg",
      "Login": "SilvanuZ_mit_Z",
      "CurrentFollowersCount": 333,
      "CurrentTweetsCout": 8612,
      "FollowersCountHistory": {},
      "TweetsCountHistory": {},
      "LangId": "de",
      "FollowersTrend": {
        "ErrorMessage": null,
        "WeeklyGrowth": 0.0,
        "WeeklyTrendLine": {
          "Start": {
            "X": 20210824.0,
            "Y": 333.428571428571
          },
          "End": {
            "X": 20210830.0,
            "Y": 333.428571428571
          }
        }
      }
    },
    "Project_AE_": {
      "PublicName": "Project AE",
      "AvatarImage": "https://pbs.twimg.com/profile_images/1392080808043757570/gB8ikxQ__normal.jpg",
      "Login": "Project_AE_",
      "CurrentFollowersCount": 656,
      "CurrentTweetsCout": 5169,
      "FollowersCountHistory": {},
      "TweetsCountHistory": {},
      "LangId": "de",
      "FollowersTrend": {
        "ErrorMessage": null,
        "WeeklyGrowth": -0.2924134943412573780256717451,
        "WeeklyTrendLine": {
          "Start": {
            "X": 20211218.0,
            "Y": 659.5357142857142857142857
          },
          "End": {
            "X": 20211224.0,
            "Y": 657.6071428571428571428571
          }
        }
      }
    },
    "PlatinMoralle": {
      "PublicName": "Moralle",
      "AvatarImage": "https://pbs.twimg.com/profile_images/1466026003554263041/vc9rcTdg_normal.jpg",
      "Login": "PlatinMoralle",
      "CurrentFollowersCount": 209,
      "CurrentTweetsCout": 10360,
      "FollowersCountHistory": {},
      "TweetsCountHistory": {},
      "LangId": "de",
      "FollowersTrend": {
        "ErrorMessage": null,
        "WeeklyGrowth": 0.5157297576070139247034416366,
        "WeeklyTrendLine": {
          "Start": {
            "X": 20211218.0,
            "Y": 207.7500000000000000000000
          },
          "End": {
            "X": 20211224.0,
            "Y": 208.8214285714285714285714
          }
        }
      }
    },
    "MoonlitMonitors": {
      "PublicName": "Moonlit Monitors",
      "AvatarImage": "https://pbs.twimg.com/profile_images/1324451182677512192/I5qG5sjY_normal.jpg",
      "Login": "MoonlitMonitors",
      "CurrentFollowersCount": 862,
      "CurrentTweetsCout": 3118,
      "FollowersCountHistory": {},
      "TweetsCountHistory": {},
      "LangId": "de",
      "FollowersTrend": {
        "ErrorMessage": null,
        "WeeklyGrowth": 1.8764263375876933479840935896,
        "WeeklyTrendLine": {
          "Start": {
            "X": 20211218.0,
            "Y": 845.071428571428571428571
          },
          "End": {
            "X": 20211224.0,
            "Y": 860.928571428571428571428
          }
        }
      }
    },
    "maogamedev": {
      "PublicName": "Mao",
      "AvatarImage": "https://pbs.twimg.com/profile_images/1346209451406221313/592F_chx_normal.jpg",
      "Login": "maogamedev",
      "CurrentFollowersCount": 240,
      "CurrentTweetsCout": 168,
      "FollowersCountHistory": {},
      "TweetsCountHistory": {},
      "LangId": "de",
      "FollowersTrend": {
        "ErrorMessage": null,
        "WeeklyGrowth": 0.0,
        "WeeklyTrendLine": {
          "Start": {
            "X": 20211218.0,
            "Y": 240.0
          },
          "End": {
            "X": 20211224.0,
            "Y": 240.0
          }
        }
      }
    },
    "Neko123Uchiha": {
      "PublicName": "Franzi | ❄️🎅",
      "AvatarImage": "https://pbs.twimg.com/profile_images/1440231475618611214/B0hwg0xb_normal.jpg",
      "Login": "Neko123Uchiha",
      "CurrentFollowersCount": 2351,
      "CurrentTweetsCout": 129197,
      "FollowersCountHistory": {},
      "TweetsCountHistory": {},
      "LangId": "de",
      "FollowersTrend": {
        "ErrorMessage": null,
        "WeeklyGrowth": -0.3091190108191653786708003196,
        "WeeklyTrendLine": {
          "Start": {
            "X": 20211218.0,
            "Y": 2356.928571428571428571429
          },
          "End": {
            "X": 20211224.0,
            "Y": 2349.642857142857142857143
          }
        }
      }
    },
    "pixeling_vince": {
      "PublicName": "Quakmann",
      "AvatarImage": "https://pbs.twimg.com/profile_images/1460583709577461768/JiuQrpQF_normal.jpg",
      "Login": "pixeling_vince",
      "CurrentFollowersCount": 125,
      "CurrentTweetsCout": 121,
      "FollowersCountHistory": {},
      "TweetsCountHistory": {},
      "LangId": "de",
      "FollowersTrend": {
        "ErrorMessage": null,
        "WeeklyGrowth": -1.018675721561969439728341707,
        "WeeklyTrendLine": {
          "Start": {
            "X": 20211218.0,
            "Y": 126.2142857142857142857143
          },
          "End": {
            "X": 20211224.0,
            "Y": 124.9285714285714285714286
          }
        }
      }
    },
    "Obvious_Dev": {
      "PublicName": "Obvious_Dev",
      "AvatarImage": "https://pbs.twimg.com/profile_images/1400542887629180935/gVGS3ort_normal.png",
      "Login": "Obvious_Dev",
      "CurrentFollowersCount": 405,
      "CurrentTweetsCout": 291,
      "FollowersCountHistory": {},
      "TweetsCountHistory": {},
      "LangId": "de",
      "FollowersTrend": {
        "ErrorMessage": null,
        "WeeklyGrowth": 0.7990766225694752730177750155,
        "WeeklyTrendLine": {
          "Start": {
            "X": 20211218.0,
            "Y": 402.250000000000000000000
          },
          "End": {
            "X": 20211224.0,
            "Y": 405.464285714285714285714
          }
        }
      }
    },
    "TinyArtJar": {
      "PublicName": "Martina (Commissions Closed)",
      "AvatarImage": "https://pbs.twimg.com/profile_images/1415311967477174278/6u7BTDk6_normal.jpg",
      "Login": "TinyArtJar",
      "CurrentFollowersCount": 3798,
      "CurrentTweetsCout": 6238,
      "FollowersCountHistory": {},
      "TweetsCountHistory": {},
      "LangId": "de",
      "FollowersTrend": {
        "ErrorMessage": null,
        "WeeklyGrowth": 0.0395082167684160027091348638,
        "WeeklyTrendLine": {
          "Start": {
            "X": 20211218.0,
            "Y": 3796.6785714285714285714286
          },
          "End": {
            "X": 20211224.0,
            "Y": 3798.1785714285714285714286
          }
        }
      }
    },
    "Gangnam_KID": {
      "PublicName": "Fluffy-Pixel-Artist",
      "AvatarImage": "https://pbs.twimg.com/profile_images/1294717860380577795/cc-btpqX_normal.jpg",
      "Login": "Gangnam_KID",
      "CurrentFollowersCount": 116,
      "CurrentTweetsCout": 37480,
      "FollowersCountHistory": {},
      "TweetsCountHistory": {},
      "LangId": "de",
      "FollowersTrend": {
        "ErrorMessage": null,
        "WeeklyGrowth": 0.0,
        "WeeklyTrendLine": {
          "Start": {
            "X": 20211218.0,
            "Y": 116.0
          },
          "End": {
            "X": 20211224.0,
            "Y": 116.0
          }
        }
      }
    },
    "DerNaderer": {
      "PublicName": "Pixeltier 🥟",
      "AvatarImage": "https://pbs.twimg.com/profile_images/1420059611609112580/ywKOEZsE_normal.png",
      "Login": "DerNaderer",
      "CurrentFollowersCount": 987,
      "CurrentTweetsCout": 1961,
      "FollowersCountHistory": {},
      "TweetsCountHistory": {},
      "LangId": "de",
      "FollowersTrend": {
        "ErrorMessage": null,
        "WeeklyGrowth": 0.3047232097511427120365667852,
        "WeeklyTrendLine": {
          "Start": {
            "X": 20211218.0,
            "Y": 984.5
          },
          "End": {
            "X": 20211224.0,
            "Y": 987.5
          }
        }
      }
    },
    "Zugai89": {
      "PublicName": "Zugai @MythiaryStudios🎮",
      "AvatarImage": "https://pbs.twimg.com/profile_images/1467194278535434243/SGAf-x5c_normal.jpg",
      "Login": "Zugai89",
      "CurrentFollowersCount": 1738,
      "CurrentTweetsCout": 13677,
      "FollowersCountHistory": {},
      "TweetsCountHistory": {},
      "LangId": "de",
      "FollowersTrend": {
        "ErrorMessage": null,
        "WeeklyGrowth": -0.0369602266893903615942144931,
        "WeeklyTrendLine": {
          "Start": {
            "X": 20211218.0,
            "Y": 1739.3214285714285714285714
          },
          "End": {
            "X": 20211224.0,
            "Y": 1738.6785714285714285714286
          }
        }
      }
    },
    "LupoBoopo": {
      "PublicName": "Lupo",
      "AvatarImage": "https://pbs.twimg.com/profile_images/1363601311837671433/iVgv9OX2_normal.jpg",
      "Login": "LupoBoopo",
      "CurrentFollowersCount": 38,
      "CurrentTweetsCout": 54,
      "FollowersCountHistory": {},
      "TweetsCountHistory": {},
      "LangId": "de",
      "FollowersTrend": {
        "ErrorMessage": null,
        "WeeklyGrowth": 0.0,
        "WeeklyTrendLine": {
          "Start": {
            "X": 20211218.0,
            "Y": 38.0
          },
          "End": {
            "X": 20211224.0,
            "Y": 38.0
          }
        }
      }
    },
    "kampyii": {
      "PublicName": "Kampyii™",
      "AvatarImage": "https://pbs.twimg.com/profile_images/1457449625326063623/IISBlC0f_normal.jpg",
      "Login": "kampyii",
      "CurrentFollowersCount": 58,
      "CurrentTweetsCout": 1417,
      "FollowersCountHistory": {},
      "TweetsCountHistory": {},
      "LangId": "de",
      "FollowersTrend": {
        "ErrorMessage": null,
        "WeeklyGrowth": 3.4242232086239695624604202533,
        "WeeklyTrendLine": {
          "Start": {
            "X": 20211218.0,
            "Y": 56.3214285714285714285714
          },
          "End": {
            "X": 20211224.0,
            "Y": 58.2500000000000000000000
          }
        }
      }
    },
    "robotriotDotOrg": {
      "PublicName": "Hannes Drexl",
      "AvatarImage": "https://pbs.twimg.com/profile_images/760535958584516608/bE1-m7Dt_normal.jpg",
      "Login": "robotriotDotOrg",
      "CurrentFollowersCount": 28,
      "CurrentTweetsCout": 14,
      "FollowersCountHistory": {},
      "TweetsCountHistory": {},
      "LangId": "de",
      "FollowersTrend": {
        "ErrorMessage": null,
        "WeeklyGrowth": 0.0,
        "WeeklyTrendLine": {
          "Start": {
            "X": 20211218.0,
            "Y": 28.0
          },
          "End": {
            "X": 20211224.0,
            "Y": 28.0
          }
        }
      }
    },
    "bwalter_indie": {
      "PublicName": "b walter",
      "AvatarImage": "https://pbs.twimg.com/profile_images/1347185987584188417/WLeAUVWJ_normal.jpg",
      "Login": "bwalter_indie",
      "CurrentFollowersCount": 3617,
      "CurrentTweetsCout": 8102,
      "FollowersCountHistory": {},
      "TweetsCountHistory": {},
      "LangId": "de",
      "FollowersTrend": {
        "ErrorMessage": null,
        "WeeklyGrowth": 0.2135906969385333438810141772,
        "WeeklyTrendLine": {
          "Start": {
            "X": 20211218.0,
            "Y": 3611.714285714285714285714
          },
          "End": {
            "X": 20211224.0,
            "Y": 3619.428571428571428571428
          }
        }
      }
    },
    "Mosaique_L": {
      "PublicName": "mikan",
      "AvatarImage": "https://pbs.twimg.com/profile_images/1450949983721697281/klqGqF_N_normal.jpg",
      "Login": "Mosaique_L",
      "CurrentFollowersCount": 175,
      "CurrentTweetsCout": 651,
      "FollowersCountHistory": {},
      "TweetsCountHistory": {},
      "LangId": "de",
      "FollowersTrend": {
        "ErrorMessage": null,
        "WeeklyGrowth": 1.49006622516556,
        "WeeklyTrendLine": {
          "Start": {
            "X": 20211017.0,
            "Y": 172.571428571429
          },
          "End": {
            "X": 20211023.0,
            "Y": 175.142857142857
          }
        }
      }
    },
    "risu_ika": {
      "PublicName": "Squirrelsquid",
      "AvatarImage": "https://pbs.twimg.com/profile_images/1365466900390699009/Gg1HF_p6_normal.jpg",
      "Login": "risu_ika",
      "CurrentFollowersCount": 1208,
      "CurrentTweetsCout": 9417,
      "FollowersCountHistory": {},
      "TweetsCountHistory": {},
      "LangId": "de",
      "FollowersTrend": {
        "ErrorMessage": null,
        "WeeklyGrowth": 1.0022670325736785586445529168,
        "WeeklyTrendLine": {
          "Start": {
            "X": 20211218.0,
            "Y": 1197.285714285714285714286
          },
          "End": {
            "X": 20211224.0,
            "Y": 1209.285714285714285714286
          }
        }
      }
    },
    "sibachmann": {
      "PublicName": "Simon Bachmann",
      "AvatarImage": "https://pbs.twimg.com/profile_images/458847597193469952/eweROjtc_normal.png",
      "Login": "sibachmann",
      "CurrentFollowersCount": 5256,
      "CurrentTweetsCout": 7445,
      "FollowersCountHistory": {},
      "TweetsCountHistory": {},
      "LangId": "de",
      "FollowersTrend": {
        "ErrorMessage": null,
        "WeeklyGrowth": -0.0244561894539476365810244425,
        "WeeklyTrendLine": {
          "Start": {
            "X": 20211218.0,
            "Y": 5257.2142857142857142857143
          },
          "End": {
            "X": 20211224.0,
            "Y": 5255.9285714285714285714286
          }
        }
      }
    },
    "yelta8": {
      "PublicName": "Yelta",
      "AvatarImage": "https://pbs.twimg.com/profile_images/1378328004460437505/7vZWY43e_normal.jpg",
      "Login": "yelta8",
      "CurrentFollowersCount": 1314,
      "CurrentTweetsCout": 1333,
      "FollowersCountHistory": {},
      "TweetsCountHistory": {},
      "LangId": "de",
      "FollowersTrend": {
        "ErrorMessage": null,
        "WeeklyGrowth": 0.803959637944707,
        "WeeklyTrendLine": {
          "Start": {
            "X": 20211123.0,
            "Y": 1306.03571428571
          },
          "End": {
            "X": 20211129.0,
            "Y": 1316.53571428571
          }
        }
      }
    },
    "lennsan_": {
      "PublicName": "lennart butz",
      "AvatarImage": "https://pbs.twimg.com/profile_images/893158175825723393/j_2xYciI_normal.jpg",
      "Login": "lennsan_",
      "CurrentFollowersCount": 7362,
      "CurrentTweetsCout": 1442,
      "FollowersCountHistory": {},
      "TweetsCountHistory": {},
      "LangId": "de",
      "FollowersTrend": {
        "ErrorMessage": null,
        "WeeklyGrowth": -0.0494380061942913643435670054,
        "WeeklyTrendLine": {
          "Start": {
            "X": 20211218.0,
            "Y": 7368.535714285714285714285
          },
          "End": {
            "X": 20211224.0,
            "Y": 7364.892857142857142857142
          }
        }
      }
    },
    "MontysMaultier": {
      "PublicName": "Jasper",
      "AvatarImage": "https://pbs.twimg.com/profile_images/1235194337580978176/yJwZ4lfG_normal.jpg",
      "Login": "MontysMaultier",
      "CurrentFollowersCount": 31,
      "CurrentTweetsCout": 66,
      "FollowersCountHistory": {},
      "TweetsCountHistory": {},
      "LangId": "de",
      "FollowersTrend": {
        "ErrorMessage": null,
        "WeeklyGrowth": 4.2959427207637231503579577469,
        "WeeklyTrendLine": {
          "Start": {
            "X": 20211218.0,
            "Y": 29.9285714285714285714285
          },
          "End": {
            "X": 20211224.0,
            "Y": 31.2142857142857142857142
          }
        }
      }
    },
    "WFGamedev": {
      "PublicName": "White Ferret Gamedev",
      "AvatarImage": "https://pbs.twimg.com/profile_images/1350906042012594184/hqf6BdA7_normal.jpg",
      "Login": "WFGamedev",
      "CurrentFollowersCount": 252,
      "CurrentTweetsCout": 574,
      "FollowersCountHistory": {},
      "TweetsCountHistory": {},
      "LangId": "de",
      "FollowersTrend": {
        "ErrorMessage": null,
        "WeeklyGrowth": -1.71735254085878,
        "WeeklyTrendLine": {
          "Start": {
            "X": 20210326.0,
            "Y": 256.213561612976
          },
          "End": {
            "X": 20210402.0,
            "Y": 251.813471502591
          }
        }
      }
    },
    "Nuraamon": {
      "PublicName": "Nuramon",
      "AvatarImage": "https://pbs.twimg.com/profile_images/1449438954575511553/_DqSK6I5_normal.jpg",
      "Login": "Nuraamon",
      "CurrentFollowersCount": 794,
      "CurrentTweetsCout": 402,
      "FollowersCountHistory": {},
      "TweetsCountHistory": {},
      "LangId": "de",
      "FollowersTrend": {
        "ErrorMessage": null,
        "WeeklyGrowth": 0.1350560482600279115833034758,
        "WeeklyTrendLine": {
          "Start": {
            "X": 20211218.0,
            "Y": 793.3214285714285714285714
          },
          "End": {
            "X": 20211224.0,
            "Y": 794.3928571428571428571428
          }
        }
      }
    },
    "TitusRabenauge": {
      "PublicName": "𝙏𝙞𝒕𝒖𝒔 𝗥𝗮𝗯𝗲𝜼𝗮𝒖𝙜𝗲",
      "AvatarImage": "https://pbs.twimg.com/profile_images/1274071254757183488/8Hn09jqp_normal.jpg",
      "Login": "TitusRabenauge",
      "CurrentFollowersCount": 97,
      "CurrentTweetsCout": 215,
      "FollowersCountHistory": {},
      "TweetsCountHistory": {},
      "LangId": "de",
      "FollowersTrend": {
        "ErrorMessage": null,
        "WeeklyGrowth": -0.2213205459240132792327495357,
        "WeeklyTrendLine": {
          "Start": {
            "X": 20211218.0,
            "Y": 96.82142857142857142857143
          },
          "End": {
            "X": 20211224.0,
            "Y": 96.60714285714285714285715
          }
        }
      }
    },
    "Shinmera": {
      "PublicName": "Shinmera",
      "AvatarImage": "https://pbs.twimg.com/profile_images/1437845175188008961/NUo0q0K3_normal.jpg",
      "Login": "Shinmera",
      "CurrentFollowersCount": 932,
      "CurrentTweetsCout": 43046,
      "FollowersCountHistory": {},
      "TweetsCountHistory": {},
      "LangId": "de",
      "FollowersTrend": {
        "ErrorMessage": null,
        "WeeklyGrowth": -0.1376673040152963671128091736,
        "WeeklyTrendLine": {
          "Start": {
            "X": 20211218.0,
            "Y": 933.9285714285714285714286
          },
          "End": {
            "X": 20211224.0,
            "Y": 932.6428571428571428571429
          }
        }
      }
    },
    "ssero": {
      "PublicName": "Markus Rosse",
      "AvatarImage": "https://pbs.twimg.com/profile_images/1318215857529626627/Mdv93LPV_normal.png",
      "Login": "ssero",
      "CurrentFollowersCount": 1036,
      "CurrentTweetsCout": 3062,
      "FollowersCountHistory": {},
      "TweetsCountHistory": {},
      "LangId": "de",
      "FollowersTrend": {
        "ErrorMessage": null,
        "WeeklyGrowth": -0.0620240515488783984011522682,
        "WeeklyTrendLine": {
          "Start": {
            "X": 20211218.0,
            "Y": 1036.4642857142857142857143
          },
          "End": {
            "X": 20211224.0,
            "Y": 1035.8214285714285714285715
          }
        }
      }
    },
    "CrackpotGames": {
      "PublicName": "Crackpot",
      "AvatarImage": "https://pbs.twimg.com/profile_images/1211977721326309376/zEXuB0fc_normal.png",
      "Login": "CrackpotGames",
      "CurrentFollowersCount": 3026,
      "CurrentTweetsCout": 1674,
      "FollowersCountHistory": {},
      "TweetsCountHistory": {},
      "LangId": "de",
      "FollowersTrend": {
        "ErrorMessage": null,
        "WeeklyGrowth": -0.0141599603521110140891614941,
        "WeeklyTrendLine": {
          "Start": {
            "X": 20211218.0,
            "Y": 3026.6428571428571428571429
          },
          "End": {
            "X": 20211224.0,
            "Y": 3026.2142857142857142857143
          }
        }
      }
    },
    "bitbrain_": {
      "PublicName": "〽️ɪɢᴜᴇʟ 🎅",
      "AvatarImage": "https://pbs.twimg.com/profile_images/1466462814856429571/JiSZMOn8_normal.png",
      "Login": "bitbrain_",
      "CurrentFollowersCount": 1687,
      "CurrentTweetsCout": 30281,
      "FollowersCountHistory": {},
      "TweetsCountHistory": {},
      "LangId": "de",
      "FollowersTrend": {
        "ErrorMessage": null,
        "WeeklyGrowth": 2.0306538187932483994048589105,
        "WeeklyTrendLine": {
          "Start": {
            "X": 20211218.0,
            "Y": 1656.75000000000000000000
          },
          "End": {
            "X": 20211224.0,
            "Y": 1690.39285714285714285714
          }
        }
      }
    },
    "Kaktuspirat": {
      "PublicName": "My Friend the Reaper",
      "AvatarImage": "https://pbs.twimg.com/profile_images/1438163218397028359/D0_bWw3G_normal.png",
      "Login": "Kaktuspirat",
      "CurrentFollowersCount": 464,
      "CurrentTweetsCout": 224,
      "FollowersCountHistory": {},
      "TweetsCountHistory": {},
      "LangId": "de",
      "FollowersTrend": {
        "ErrorMessage": null,
        "WeeklyGrowth": 8.974464920254524419468113463,
        "WeeklyTrendLine": {
          "Start": {
            "X": 20211218.0,
            "Y": 432.17857142857142857143
          },
          "End": {
            "X": 20211224.0,
            "Y": 470.96428571428571428571
          }
        }
      }
    },
    "Tscholdes": {
      "PublicName": "Tscholdes",
      "AvatarImage": "https://pbs.twimg.com/profile_images/1136681178340167680/50KoF6x0_normal.png",
      "Login": "Tscholdes",
      "CurrentFollowersCount": 2180,
      "CurrentTweetsCout": 160,
      "FollowersCountHistory": {},
      "TweetsCountHistory": {},
      "LangId": "de",
      "FollowersTrend": {
        "ErrorMessage": null,
        "WeeklyGrowth": 1.021639582747846787125337586,
        "WeeklyTrendLine": {
          "Start": {
            "X": 20211218.0,
            "Y": 2160.392857142857142857143
          },
          "End": {
            "X": 20211224.0,
            "Y": 2182.464285714285714285714
          }
        }
      }
    },
    "Okosano_pixel": {
      "PublicName": "Okosano | xXRukiaXx",
      "AvatarImage": "https://pbs.twimg.com/profile_images/1465059352323272712/g5sJ6KUJ_normal.jpg",
      "Login": "Okosano_pixel",
      "CurrentFollowersCount": 120,
      "CurrentTweetsCout": 492,
      "FollowersCountHistory": {},
      "TweetsCountHistory": {},
      "LangId": "de",
      "FollowersTrend": {
        "ErrorMessage": null,
        "WeeklyGrowth": 0.9022556390977443609022315789,
        "WeeklyTrendLine": {
          "Start": {
            "X": 20211218.0,
            "Y": 118.7500000000000000000000
          },
          "End": {
            "X": 20211224.0,
            "Y": 119.8214285714285714285714
          }
        }
      }
    },
    "MV_Raffa": {
      "PublicName": "Raffaele Picca",
      "AvatarImage": "https://pbs.twimg.com/profile_images/1431939257761947648/G1FDUTZ7_normal.jpg",
      "Login": "MV_Raffa",
      "CurrentFollowersCount": 2064,
      "CurrentTweetsCout": 1074,
      "FollowersCountHistory": {},
      "TweetsCountHistory": {},
      "LangId": "de",
      "FollowersTrend": {
        "ErrorMessage": null,
        "WeeklyGrowth": 1.4094706536905876326898251561,
        "WeeklyTrendLine": {
          "Start": {
            "X": 20211218.0,
            "Y": 2022.03571428571428571429
          },
          "End": {
            "X": 20211224.0,
            "Y": 2050.53571428571428571429
          }
        }
      }
    },
    "BloomJrArt": {
      "PublicName": "Bloom Jr.",
      "AvatarImage": "https://pbs.twimg.com/profile_images/1446930612691087361/ajjsAZY1_normal.jpg",
      "Login": "BloomJrArt",
      "CurrentFollowersCount": 1582,
      "CurrentTweetsCout": 8217,
      "FollowersCountHistory": {},
      "TweetsCountHistory": {},
      "LangId": "de",
      "FollowersTrend": {
        "ErrorMessage": null,
        "WeeklyGrowth": 0.2993333030976461517528957415,
        "WeeklyTrendLine": {
          "Start": {
            "X": 20211218.0,
            "Y": 1574.928571428571428571429
          },
          "End": {
            "X": 20211224.0,
            "Y": 1579.642857142857142857143
          }
        }
      }
    },
    "IdinaKloppstock": {
      "PublicName": "Idina Kloppstock",
      "AvatarImage": "https://pbs.twimg.com/profile_images/1450565502913368066/4ncylwYJ_normal.jpg",
      "Login": "IdinaKloppstock",
      "CurrentFollowersCount": 64,
      "CurrentTweetsCout": 181,
      "FollowersCountHistory": {},
      "TweetsCountHistory": {},
      "LangId": "de",
      "FollowersTrend": {
        "ErrorMessage": null,
        "WeeklyGrowth": 0.0,
        "WeeklyTrendLine": {
          "Start": {
            "X": 20211218.0,
            "Y": 64.428571428571428571428571429
          },
          "End": {
            "X": 20211224.0,
            "Y": 64.428571428571428571428571429
          }
        }
      }
    },
    "DerNachbart": {
      "PublicName": "DerNachbar",
      "AvatarImage": "https://pbs.twimg.com/profile_images/853884065505824768/kG6H2f_Z_normal.jpg",
      "Login": "DerNachbart",
      "CurrentFollowersCount": 1024,
      "CurrentTweetsCout": 1518,
      "FollowersCountHistory": {},
      "TweetsCountHistory": {},
      "LangId": "de",
      "FollowersTrend": {
        "ErrorMessage": null,
        "WeeklyGrowth": -0.1045478306325143753267091857,
        "WeeklyTrendLine": {
          "Start": {
            "X": 20211218.0,
            "Y": 1024.8214285714285714285714
          },
          "End": {
            "X": 20211224.0,
            "Y": 1023.7500000000000000000000
          }
        }
      }
    },
    "ChippixOfficial": {
      "PublicName": "Chippix",
      "AvatarImage": "https://pbs.twimg.com/profile_images/1242813752367611905/s7WOz9xV_normal.jpg",
      "Login": "ChippixOfficial",
      "CurrentFollowersCount": 181,
      "CurrentTweetsCout": 2330,
      "FollowersCountHistory": {},
      "TweetsCountHistory": {},
      "LangId": "de",
      "FollowersTrend": {
        "ErrorMessage": null,
        "WeeklyGrowth": 0.5960659646334194317504311544,
        "WeeklyTrendLine": {
          "Start": {
            "X": 20211218.0,
            "Y": 179.7500000000000000000000
          },
          "End": {
            "X": 20211224.0,
            "Y": 180.8214285714285714285714
          }
        }
      }
    },
    "ghostundermoon": {
      "PublicName": "MoonGhost",
      "AvatarImage": "https://pbs.twimg.com/profile_images/1453591305871888387/sFHwk2_J_normal.jpg",
      "Login": "ghostundermoon",
      "CurrentFollowersCount": 3281,
      "CurrentTweetsCout": 656,
      "FollowersCountHistory": {},
      "TweetsCountHistory": {},
      "LangId": "de",
      "FollowersTrend": {
        "ErrorMessage": null,
        "WeeklyGrowth": 0.176634138363408384669910032,
        "WeeklyTrendLine": {
          "Start": {
            "X": 20211218.0,
            "Y": 3275.535714285714285714286
          },
          "End": {
            "X": 20211224.0,
            "Y": 3281.321428571428571428572
          }
        }
      }
    },
    "ruedischmuedi": {
      "PublicName": "🎀rüdi",
      "AvatarImage": "https://pbs.twimg.com/profile_images/1459636804764807172/DHhBnanP_normal.jpg",
      "Login": "ruedischmuedi",
      "CurrentFollowersCount": 265,
      "CurrentTweetsCout": 738,
      "FollowersCountHistory": {},
      "TweetsCountHistory": {},
      "LangId": "de",
      "FollowersTrend": {
        "ErrorMessage": null,
        "WeeklyGrowth": 0.4882017900732302685109791953,
        "WeeklyTrendLine": {
          "Start": {
            "X": 20211218.0,
            "Y": 263.3571428571428571428571
          },
          "End": {
            "X": 20211224.0,
            "Y": 264.6428571428571428571428
          }
        }
      }
    },
    "PixelAndre_": {
      "PublicName": "Andre",
      "AvatarImage": "https://pbs.twimg.com/profile_images/1049176082455437312/UlOMBIGd_normal.jpg",
      "Login": "PixelAndre_",
      "CurrentFollowersCount": 227,
      "CurrentTweetsCout": 4428,
      "FollowersCountHistory": {},
      "TweetsCountHistory": {},
      "LangId": "de",
      "FollowersTrend": {
        "ErrorMessage": null,
        "WeeklyGrowth": 0.0,
        "WeeklyTrendLine": {
          "Start": {
            "X": 20211218.0,
            "Y": 227.0
          },
          "End": {
            "X": 20211224.0,
            "Y": 227.0
          }
        }
      }
    },
    "fluxfruit": {
      "PublicName": "Flux🔞",
      "AvatarImage": "https://pbs.twimg.com/profile_images/1470529361271005185/lfvCmTh1_normal.jpg",
      "Login": "fluxfruit",
      "CurrentFollowersCount": 82,
      "CurrentTweetsCout": 208,
      "FollowersCountHistory": {},
      "TweetsCountHistory": {},
      "LangId": "de",
      "FollowersTrend": {
        "ErrorMessage": null,
        "WeeklyGrowth": 2.9904848210240144993201793774,
        "WeeklyTrendLine": {
          "Start": {
            "X": 20211218.0,
            "Y": 78.821428571428571428571
          },
          "End": {
            "X": 20211224.0,
            "Y": 81.178571428571428571428
          }
        }
      }
    },
    "BBits21": {
      "PublicName": "BurnedBits",
      "AvatarImage": "https://pbs.twimg.com/profile_images/1195325698434641925/VgaOOH05_normal.jpg",
      "Login": "BBits21",
      "CurrentFollowersCount": 107,
      "CurrentTweetsCout": 785,
      "FollowersCountHistory": {},
      "TweetsCountHistory": {},
      "LangId": "de",
      "FollowersTrend": {
        "ErrorMessage": null,
        "WeeklyGrowth": 0.0,
        "WeeklyTrendLine": {
          "Start": {
            "X": 20211218.0,
            "Y": 107.0
          },
          "End": {
            "X": 20211224.0,
            "Y": 107.0
          }
        }
      }
    },
    "strahl_leo": {
      "PublicName": "ライオン pixelart",
      "AvatarImage": "https://pbs.twimg.com/profile_images/1437686263067385861/roqYGhBC_normal.jpg",
      "Login": "strahl_leo",
      "CurrentFollowersCount": 56,
      "CurrentTweetsCout": 129,
      "FollowersCountHistory": {},
      "TweetsCountHistory": {},
      "LangId": "de",
      "FollowersTrend": {
        "ErrorMessage": null,
        "WeeklyGrowth": 0.0,
        "WeeklyTrendLine": {
          "Start": {
            "X": 20211218.0,
            "Y": 56.0
          },
          "End": {
            "X": 20211224.0,
            "Y": 56.0
          }
        }
      }
    },
    "MangoJu75930414": {
      "PublicName": "MangoJuice",
      "AvatarImage": "https://pbs.twimg.com/profile_images/1323262122919448577/t920j8TK_normal.jpg",
      "Login": "MangoJu75930414",
      "CurrentFollowersCount": 3704,
      "CurrentTweetsCout": 483,
      "FollowersCountHistory": {},
      "TweetsCountHistory": {},
      "LangId": "de",
      "FollowersTrend": {
        "ErrorMessage": null,
        "WeeklyGrowth": 3.7988649126817680326809713648,
        "WeeklyTrendLine": {
          "Start": {
            "X": 20211218.0,
            "Y": 3593.17857142857142857143
          },
          "End": {
            "X": 20211224.0,
            "Y": 3729.67857142857142857143
          }
        }
      }
    },
    "awsm9000": {
      "PublicName": "awsm",
      "AvatarImage": "https://pbs.twimg.com/profile_images/1184102037593710594/Rximt31E_normal.jpg",
      "Login": "awsm9000",
      "CurrentFollowersCount": 3120,
      "CurrentTweetsCout": 2204,
      "FollowersCountHistory": {},
      "TweetsCountHistory": {},
      "LangId": "de",
      "FollowersTrend": {
        "ErrorMessage": null,
        "WeeklyGrowth": 0.2341866605441395936172747424,
        "WeeklyTrendLine": {
          "Start": {
            "X": 20211218.0,
            "Y": 3111.071428571428571428571
          },
          "End": {
            "X": 20211224.0,
            "Y": 3118.357142857142857142857
          }
        }
      }
    },
    "Shiruht1": {
      "PublicName": "Shiruht",
      "AvatarImage": "https://pbs.twimg.com/profile_images/1462581005596995587/Kv5I2E6y_normal.jpg",
      "Login": "Shiruht1",
      "CurrentFollowersCount": 1684,
      "CurrentTweetsCout": 6533,
      "FollowersCountHistory": {},
      "TweetsCountHistory": {},
      "LangId": "de",
      "FollowersTrend": {
        "ErrorMessage": null,
        "WeeklyGrowth": 6.5597667638483965014579081633,
        "WeeklyTrendLine": {
          "Start": {
            "X": 20211218.0,
            "Y": 1568.00000000000000000000
          },
          "End": {
            "X": 20211224.0,
            "Y": 1670.85714285714285714286
          }
        }
      }
    },
    "thesaddestalive": {
      "PublicName": "thesaddestguyalive",
      "AvatarImage": "https://pbs.twimg.com/profile_images/1465699228802420751/gaCVuxHD_normal.jpg",
      "Login": "thesaddestalive",
      "CurrentFollowersCount": 3327,
      "CurrentTweetsCout": 3910,
      "FollowersCountHistory": {},
      "TweetsCountHistory": {},
      "LangId": "de",
      "FollowersTrend": {
        "ErrorMessage": null,
        "WeeklyGrowth": 2.2998605146679260617910355962,
        "WeeklyTrendLine": {
          "Start": {
            "X": 20211218.0,
            "Y": 3251.75000000000000000000
          },
          "End": {
            "X": 20211224.0,
            "Y": 3326.53571428571428571429
          }
        }
      }
    },
    "insomniak111": {
      "PublicName": "insomniak",
      "AvatarImage": "https://pbs.twimg.com/profile_images/1452770466360397834/Q9jVCUP7_normal.jpg",
      "Login": "insomniak111",
      "CurrentFollowersCount": 11,
      "CurrentTweetsCout": 47,
      "FollowersCountHistory": {},
      "TweetsCountHistory": {},
      "LangId": "de",
      "FollowersTrend": {
        "ErrorMessage": null,
        "WeeklyGrowth": -9.063444108761329305135731875,
        "WeeklyTrendLine": {
          "Start": {
            "X": 20211218.0,
            "Y": 11.8214285714285714285714
          },
          "End": {
            "X": 20211224.0,
            "Y": 10.7500000000000000000000
          }
        }
      }
    }
  },
  "LastTimeUpdate": "2021-12-24 23:00:03"
}